examples/__init__.py
gp_lib/__init__.py
gp_lib/algs.py
gp_lib/gp.py
gp_lib/kernels.py
gp_lib/sparse.py
gp_lib/utils.py
gp_lib-0.0.4.dist-info/LICENSE
gp_lib-0.0.4.dist-info/METADATA
gp_lib-0.0.4.dist-info/WHEEL
gp_lib-0.0.4.dist-info/top_level.txt
gp_lib-0.0.4.dist-info/RECORD
